blkcache/__init__.py
blkcache/backend.py
blkcache/ddrescue.py
blkcache/main.py
blkcache/server.py
blkcache/file/__init__.py
blkcache/file/atomic.py
blkcache/file/base.py
blkcache/file/cached.py
blkcache/file/device.py
blkcache/file/filemap.py
blkcache/file/mmapped.py
blkcache/file/removable.py
blkcache-0.0.2.dist-info/entry_points.txt
blkcache-0.0.2.dist-info/licenses/LICENSE.md
blkcache-0.0.2.dist-info/WHEEL
blkcache-0.0.2.dist-info/METADATA
blkcache-0.0.2.dist-info/RECORD
