Metadata-Version: 2.4
Name: blkcache
Version: 0.0.2
Summary: A block device cache in userspace
Author-email: Gareth Davidson <gaz@bitplane.net>
Requires-Python: >=3.10
Classifier: Development Status :: 2 - Pre-Alpha
Classifier: Programming Language :: Python :: 3
Classifier: Programming Language :: Python :: 3.10
Classifier: Programming Language :: Python :: 3.11
Classifier: License :: Public Domain
Classifier: Environment :: Console
Classifier: Intended Audience :: Developers
License-File: LICENSE.md
Requires-Dist: pre-commit ; extra == "dev"
Requires-Dist: pytest ; extra == "dev"
Requires-Dist: coverage ; extra == "dev"
Requires-Dist: pytest-cov ; extra == "dev"
Requires-Dist: pydoc-markdown ; extra == "dev"
Requires-Dist: build ; extra == "dev"
Requires-Dist: twine ; extra == "dev"
Requires-Dist: ruff ; extra == "dev"
Requires-Dist: mkdocs ; extra == "dev"
Project-URL: Bug Tracker, https://github.com/bitplane/blkcache/issues
Project-URL: Homepage, https://github.com/bitplane/blkcache
Project-URL: Source Code, https://github.com/bitplane/blkcache
Provides-Extra: dev
